seeed_sgp30.py
seeed_python_sgp30-0.1.0.dist-info/LICENSE
seeed_python_sgp30-0.1.0.dist-info/METADATA
seeed_python_sgp30-0.1.0.dist-info/WHEEL
seeed_python_sgp30-0.1.0.dist-info/top_level.txt
seeed_python_sgp30-0.1.0.dist-info/RECORD
