Metadata-Version: 2.1
Name: seeed-python-sgp30
Version: 0.1.0
Summary: Python library for the Grove-VOC and eCO2 Gas Sensor(SGP30) is an air quality detection sensor. 
Home-page: https://github.com/Seeed-Studio/Seeed_Python_SGP30
Author: Baozhu Zuo
Author-email: zuobaozhu@gmail.com
License: MIT
Keywords: seeed grove sgp30 gas sensor eco2 tvoc i2c hardware
Platform: UNKNOWN
Classifier: Development Status :: 3 - Alpha
Classifier: Intended Audience :: Developers
Classifier: Topic :: Software Development :: Libraries
Classifier: Topic :: System :: Hardware
Classifier: License :: OSI Approved :: MIT License
Classifier: Programming Language :: Python :: 3
Classifier: Programming Language :: Python :: 3.4
Classifier: Programming Language :: Python :: 3.5
Requires-Dist: sgp30
